SacherECLControl/Helpers.py
SacherECLControl/LaserConfig.py
SacherECLControl/__init__.py
SacherECLControl/controller/LaserDeviceControl.py
SacherECLControl/controller/__init__.py
SacherECLControl/controller/multiprocess/MPLaserDevice.py
SacherECLControl/libs/LaserLibSimulator.py
SacherECLControl/libs/LaserSceleton.py
SacherECLControl/libs/__init__.py
SacherECLControl/libs/sweepHelpers.py
SacherECLControl/model/LaserControlModel.py
SacherECLControl/model/LaserControlSignals.py
SacherECLControl/model/__init__.py
SacherECLControl/resources/LaserControlWindow.ui
SacherECLControl/resources/convert.sh
SacherECLControl/resources/resources.qrc
SacherECLControl/resources/icons/cil-3d.png
SacherECLControl/resources/icons/cil-4k.png
SacherECLControl/resources/icons/cil-account-logout.png
SacherECLControl/resources/icons/cil-action-redo.png
SacherECLControl/resources/icons/cil-action-undo.png
SacherECLControl/resources/icons/cil-airplane-mode-off.png
SacherECLControl/resources/icons/cil-airplane-mode.png
SacherECLControl/resources/icons/cil-alarm.png
SacherECLControl/resources/icons/cil-align-center.png
SacherECLControl/resources/icons/cil-align-left.png
SacherECLControl/resources/icons/cil-align-right.png
SacherECLControl/resources/icons/cil-arrow-bottom-2.png
SacherECLControl/resources/icons/cil-arrow-bottom.png
SacherECLControl/resources/icons/cil-arrow-circle-bottom.png
SacherECLControl/resources/icons/cil-arrow-circle-left.png
SacherECLControl/resources/icons/cil-arrow-circle-right.png
SacherECLControl/resources/icons/cil-arrow-circle-top.png
SacherECLControl/resources/icons/cil-arrow-left.png
SacherECLControl/resources/icons/cil-arrow-right.png
SacherECLControl/resources/icons/cil-arrow-top.png
SacherECLControl/resources/icons/cil-at.png
SacherECLControl/resources/icons/cil-av-timer.png
SacherECLControl/resources/icons/cil-ban.png
SacherECLControl/resources/icons/cil-battery-0.png
SacherECLControl/resources/icons/cil-battery-3.png
pysachereclcontrol-1.2.8.dist-info/METADATA
pysachereclcontrol-1.2.8.dist-info/WHEEL
pysachereclcontrol-1.2.8.dist-info/licenses/LICENSE
pysachereclcontrol-1.2.8.dist-info/RECORD
