Metadata-Version: 2.4
Name: PySacherECLControl
Version: 1.2.8
Summary: PySacherECLControl is a python project developed to control Sacher TEC lasers. This project offers a convenient interface for users to interact with the laser, adjust parameters, and perform various operations for laser control and management.
Project-URL: Homepage, https://github.com/agentsmith29/PyADScopeControl
Author-email: Christoph Schmidt <christoph.schmidt@tugraz.at>
License-File: LICENSE
Classifier: License :: OSI Approved :: GNU General Public License v3 (GPLv3)
Classifier: Operating System :: Microsoft :: Windows
Classifier: Programming Language :: Python :: 3
Requires-Python: <3.13,>=3.12
Requires-Dist: confpy6>=1.3.1
Requires-Dist: mppy6
Requires-Dist: pyadscopecontrol>=1.1.7
Requires-Dist: pyside6
Requires-Dist: pyside6widgetcollection>=1.0.3
Requires-Dist: pyyaml
Requires-Dist: rich
